<?xml version="1.0" encoding="UTF-8"?>
<Ocean>
	<Cancellation>
		<keyword id="clickCancellationTab">
			<locator>Name</locator>
			<value>Cancellation</value>
		</keyword>
		<keyword id="clickMailservice">
			<locator>xpath</locator>
			<value>//*[@AutomationId='Mail Service']</value>
		</keyword>
		<keyword id="clickClear">
			<locator>Name</locator>
			<value>Clear</value>
		</keyword>
		<keyword id="textMessageForFeeExceeds">
			<locator>Name</locator>
			<value>Cancelation fee exceeds refund</value>
		</keyword>
		<keyword id="typeContractId">
			<locator>xpath</locator>
			<value>//*[@Name='Contract Number']/following-sibling::*[@ClassName='TextBox']</value>
		</keyword>
		<keyword id="searchContractButton">
			<locator>xpath</locator>
			<value>//*[@Name='MaterialTabControl']//*[@ClassName='ScrollViewer']//*[@Name='Search']	</value>
		</keyword>
		<keyword id="clickCancelButton">
			<locator>Name</locator>
			<value>Cancel</value>
		</keyword>
		<keyword id="swipeRight">
			<locator>xpath</locator>
			<value>//*[@AutomationId='PageRight']</value>
		</keyword>
			<keyword id="swipeLeft">
			<locator>xpath</locator>
			<value>//*[@AutomationId='PageLeft']</value>
		</keyword>
		<keyword id="statusOfContract">
			<locator>xpath</locator>
			<value>//*[@AutomationId='Row_0']//*[@Name='Status']</value>
		</keyword>
		<keyword id="selectInitiatedBy">
			<locator>xpath</locator>
			<value>//*[@Name='Initiated By:']/following-sibling::*[1]</value>
		</keyword>
		<keyword id="selectCancelReason">
			<locator>xpath</locator>
			<value>//*[@Name='Cancel Reason:']/following-sibling::*[1]</value>
		</keyword>
		<keyword id="getMiles">
			<locator>xpath</locator>
			<value>//*[@ClassName='ScrollViewer']//*[@Name='Sale Mileage']/following-sibling::*[1]</value>
		</keyword>
		<keyword id="enterCancelMiles">
			<locator>xpath</locator>
			<value>//*[@Name='Cancel Miles:']/following-sibling::*[1]</value>
		</keyword>
		<keyword id="enterCancelDate">
			<locator>xpath</locator>
			<value>//*[@Name='Cancel Date:']/following-sibling::*[1]</value>
		</keyword>
		<keyword id="enterDateReceived">
			<locator>xpath</locator>
			<value>//*[@Name='Date Received:']/following-sibling::*[1]</value>
		</keyword>
		<keyword id="clickCalculate">
			<locator>xpath</locator>
			<value>//*[@AutomationId='BtnCalculate']</value>
		</keyword>
		<keyword id="checkAuthorize">
			<locator>xpath</locator>			
			<value>//*[@AutomationId='Row_0']//*[@AutomationId='Cell_CertNumber']</value>
		</keyword>
		<keyword id="clickOK">
			<locator>Name</locator>
			<value>OK</value>
		</keyword>
		<keyword id="typeCustomerFirstName">
			<locator>xpath</locator>
			<value>//*[@Name='Customer First Name']/following-sibling::*[@ClassName='TextBox']</value>
		</keyword>
		<keyword id="inValidPayeeErrorMessage">
			<locator>Name</locator>
			<value>Invalid Payee information</value>
		</keyword>
		<keyword id="overRideRulesCheckBox">
			<locator>Name</locator>
			<value>Override Rules</value>
		</keyword>
		<keyword id="refundPercent">
			<locator>xpath</locator>
			<value>(//*[@Name='Refund%']/following-sibling::*[@ClassName='TextBox'])[2]</value>
		</keyword>
		<keyword id="cancelFee">
			<locator>xpath</locator>
			<value>(//*[@Name='Cancel Fee:']/following-sibling::*[@ClassName='TextBox'])[2]</value>
		</keyword>
		<keyword id="selectPayee">
			<locator>xpath</locator>
			<value>//*[@Name='Payee:']/following-sibling::*[1]</value>
		</keyword>
		<keyword id="clickAuthorize">
			<locator>Name</locator>
			<value>Authorize</value>
		</keyword>
	</Cancellation>
</Ocean>
